ramlpy/__init__.py
ramlpy/exc.py
ramlpy/expressions.py
ramlpy/parser.py
ramlpy/typesystem.py
ramlpy/utils.py
ramlpy/version.py
ramlpy-0.0.25.dist-info/METADATA
ramlpy-0.0.25.dist-info/RECORD
ramlpy-0.0.25.dist-info/WHEEL
ramlpy-0.0.25.dist-info/top_level.txt
